certsign/__init__.py
certsign/__main__.py
certsign/cli.py
certsign/client.py
certsign/crypto.py
certsign/server.py
certsign-0.4.1.dist-info/LICENSE.txt
certsign-0.4.1.dist-info/METADATA
certsign-0.4.1.dist-info/WHEEL
certsign-0.4.1.dist-info/entry_points.txt
certsign-0.4.1.dist-info/top_level.txt
certsign-0.4.1.dist-info/RECORD
