Metadata-Version: 2.1
Name: certsign
Version: 0.4.1
Summary: A tiny ACME (Let's Encrypt) Python 2 & 3 client library with minimal dependencies
Home-page: https://github.com/unioslo/certsign
Author: Nils Fredrik Gjerull
Author-email: n.f.gjerull@usit.uio.no
License: BSD
Keywords: acme letsencrypt
Platform: UNKNOWN
Classifier: Development Status :: 3 - Alpha
Classifier: Environment :: Console
Classifier: Intended Audience :: Developers
Classifier: Intended Audience :: System Administrators
Classifier: License :: OSI Approved :: BSD License
Classifier: Operating System :: POSIX :: Linux
Classifier: Programming Language :: Python :: 2.7
Classifier: Programming Language :: Python :: 3
Classifier: Topic :: Security
License-File: LICENSE.txt
Requires-Dist: setuptools (>=40.0)
Provides-Extra: dev
Requires-Dist: pytest ; extra == 'dev'
Requires-Dist: tox ; extra == 'dev'
Requires-Dist: twine ; extra == 'dev'
Requires-Dist: wheel ; extra == 'dev'
